sphinx_js/__init__.py
sphinx_js/analyzer_utils.py
sphinx_js/directives.py
sphinx_js/ir.py
sphinx_js/jsdoc.py
sphinx_js/parsers.py
sphinx_js/renderers.py
sphinx_js/suffix_tree.py
sphinx_js/typedoc.py
sphinx_js/js/cli.ts
sphinx_js/js/convertTopLevel.ts
sphinx_js/js/convertType.ts
sphinx_js/js/importHooks.mjs
sphinx_js/js/ir.ts
sphinx_js/js/main.ts
sphinx_js/js/package-lock.json
sphinx_js/js/package.json
sphinx_js/js/redirectPrivateAliases.ts
sphinx_js/js/registerImportHook.mjs
sphinx_js/js/sphinxJsConfig.ts
sphinx_js/js/tsconfig.json
sphinx_js/js/typedocPatches.ts
sphinx_js/js/typedocPlugin.ts
sphinx_js/templates/attribute.rst
sphinx_js/templates/class.rst
sphinx_js/templates/common.rst
sphinx_js/templates/function.rst
sphinx_js-5.0.2.dist-info/METADATA
sphinx_js-5.0.2.dist-info/WHEEL
sphinx_js-5.0.2.dist-info/licenses/LICENSE
sphinx_js-5.0.2.dist-info/RECORD
