Metadata-Version: 2.4
Name: sphinx-js
Version: 5.0.2
Summary: Support for using Sphinx on JSDoc-documented JS code
Project-URL: Homepage, https://github.com/pyodide/sphinx-js
Author-email: Hood Chatham <roberthoodchatham@gmail.com>
License: MIT
License-File: LICENSE
Keywords: docs,documentation,javascript,js,jsdoc,restructured,sphinx,typedoc,typescript
Classifier: Development Status :: 5 - Production/Stable
Classifier: Framework :: Sphinx :: Domain
Classifier: Framework :: Sphinx :: Extension
Classifier: Intended Audience :: Developers
Classifier: License :: OSI Approved :: MIT License
Classifier: Natural Language :: English
Classifier: Programming Language :: Python :: 3
Classifier: Topic :: Documentation :: Sphinx
Classifier: Topic :: Software Development :: Documentation
Requires-Python: >=3.10
Requires-Dist: attrs
Requires-Dist: cattrs<25.1
Requires-Dist: jinja2>2.0
Requires-Dist: markupsafe
Requires-Dist: parsimonious<0.11.0,>=0.10.0
Requires-Dist: sphinx>=4.1.0
Provides-Extra: test
Requires-Dist: beautifulsoup4; extra == 'test'
Requires-Dist: build; extra == 'test'
Requires-Dist: defusedxml; extra == 'test'
Requires-Dist: nox; extra == 'test'
Requires-Dist: pytest-cov; extra == 'test'
Requires-Dist: recommonmark; extra == 'test'
Requires-Dist: twine; extra == 'test'
